Metadata-Version: 2.1
Name: wifiConfig
Version: 0.1.13
Summary: Flask app for an easy wifi configuration, iot oriented.
Home-page: https://github.com/RoberWare/wifiConfig
Author: Roberto Lama Rodriguez
Author-email: roberlama@gmail.com
License: MIT
Keywords: wifi,configuration,hotspot,flask,iot,rpi,raspberry
Platform: UNKNOWN
Classifier: Development Status :: 3 - Alpha
Classifier: Intended Audience :: Developers
Classifier: Topic :: Software Development :: Build Tools
Classifier: License :: OSI Approved :: MIT License
Classifier: Programming Language :: Python :: 3
Classifier: Programming Language :: Python :: 3.4
Classifier: Programming Language :: Python :: 3.5
Classifier: Programming Language :: Python :: 3.6
